skellycam/__init__.py
skellycam/__main__.py
skellycam/detection/__init__.py
skellycam/detection/detect_cameras.py
skellycam/detection/charuco/charuco_definition.py
skellycam/detection/charuco/charuco_detection.py
skellycam/detection/models/__init__.py
skellycam/detection/models/frame_payload.py
skellycam/detection/private/detect_possible_cameras.py
skellycam/detection/private/found_camera_cache.py
skellycam/diagnostics/__init__.py
skellycam/diagnostics/create_diagnostic_plots.py
skellycam/diagnostics/plot_first_middle_and_last_frames.py
skellycam/diagnostics/plot_framerate_diagnostics.py
skellycam/examples/__init__.py
skellycam/examples/example1_single_camera_connection.py
skellycam/examples/example2_record_synchronized_videos.py
skellycam/examples/show_all_cameras_in_cv2_windows.py
skellycam/experiments/__init__.py
skellycam/experiments/cam_show.py
skellycam/experiments/imshow_tester.py
skellycam/experiments/slider_widget.py
skellycam/experiments/multi_camera_recorder/__init__.py
skellycam/experiments/multi_camera_recorder/multicamera_video_recorder.py
skellycam/gui/__init__.py
skellycam/gui/qt/__init__.py
skellycam/gui/qt/main.py
skellycam/gui/qt/skelly_cam_main_window.py
skellycam/gui/qt/skelly_cam_widget.py
skellycam/gui/qt/css/__init__.py
skellycam/gui/qt/css/qt_css_stylesheet.py
skellycam/gui/qt/utilities/__init__.py
skellycam/gui/qt/utilities/clear_layout.py
skellycam/gui/qt/utilities/get_qt_app.py
skellycam/gui/qt/utilities/qt_label_strings.py
skellycam/gui/qt/widgets/__init__.py
skellycam/gui/qt/widgets/single_camera_view_widget.py
skellycam/gui/qt/widgets/skelly_cam_config_parameter_tree_widget.py
skellycam/gui/qt/widgets/skelly_cam_controller_widget.py
skellycam/gui/qt/widgets/skelly_cam_directory_view_widget.py
skellycam/gui/qt/widgets/welcome_to_skellycam_widget.py
skellycam/gui/qt/workers/__init__.py
skellycam/gui/qt/workers/camera_group_thread_worker.py
skellycam/gui/qt/workers/detect_cameras_worker.py
skellycam/gui/qt/workers/save_videos_worker.py
skellycam-2025.9.1097.dist-info/entry_points.txt
skellycam-2025.9.1097.dist-info/licenses/LICENSE
skellycam-2025.9.1097.dist-info/WHEEL
skellycam-2025.9.1097.dist-info/METADATA
skellycam-2025.9.1097.dist-info/RECORD
