Metadata-Version: 2.4
Name: skellycam
Version: 2025.9.1097
Summary: Top-level package for skellycam.
Keywords: camera,stream,video,image,opencv,skelly,freemocap,motion capture,synchronization,computer vision
Author: Endurance Idehen, Jonathan Samir Matthis
Author-email: Skelly FreeMoCap <info@freemocap.org>
Requires-Python: >=3.9,<3.13
Classifier: Development Status :: 3 - Alpha
Classifier: License :: OSI Approved :: GNU Affero General Public License v3 or later (AGPLv3+)
Classifier: Intended Audience :: Developers
Classifier: Intended Audience :: Education
Classifier: Intended Audience :: Healthcare Industry
Classifier: Intended Audience :: Science/Research
Classifier: Intended Audience :: End Users/Desktop
Classifier: Intended Audience :: Other Audience
Classifier: Natural Language :: English
Classifier: Operating System :: OS Independent
Classifier: Programming Language :: Python :: 3
Classifier: Programming Language :: Python :: 3.8
Classifier: Programming Language :: Python :: 3.9
Classifier: Programming Language :: Python :: 3.10
Classifier: Programming Language :: Python :: 3.11
Classifier: Topic :: Software Development :: Libraries :: Python Modules
Classifier: Topic :: Utilities
Classifier: Topic :: Multimedia :: Video
Classifier: Topic :: Multimedia :: Video :: Capture
Classifier: Topic :: Multimedia :: Video :: Display
Classifier: Topic :: Scientific/Engineering
Classifier: Topic :: Scientific/Engineering :: Image Processing
Classifier: Topic :: Scientific/Engineering :: Visualization
Classifier: Topic :: Scientific/Engineering :: Human Machine Interfaces
Classifier: Topic :: System :: Hardware
Classifier: Topic :: System :: Hardware :: Universal Serial Bus (USB)
Classifier: Topic :: System :: Hardware :: Universal Serial Bus (USB) :: Video (UVC)
License-File: LICENSE
Requires-Dist: numpy==1.26.2
Requires-Dist: opencv-contrib-python==4.8.*
Requires-Dist: pydantic==2.*
Requires-Dist: Pillow==10.0.1
Requires-Dist: psutil==5.9.6
Requires-Dist: setproctitle==1.3.3
Requires-Dist: pyside6==6.6.*
Requires-Dist: matplotlib==3.8.2
Requires-Dist: scipy==1.11.4
Requires-Dist: rich==13.7.0
Requires-Dist: pandas==2.1.4
Requires-Dist: pyqtgraph==0.13.3
Requires-Dist: qtpy==2.4.1
Requires-Dist: toml==0.10.2
Requires-Dist: tqdm==4.66.1
Requires-Dist: black ; extra == "dev"
Requires-Dist: bumpver ; extra == "dev"
Requires-Dist: isort ; extra == "dev"
Requires-Dist: pip-tools ; extra == "dev"
Requires-Dist: pytest ; extra == "dev"
Project-URL: Homepage, https://github.com/freemocap/skellycam
Provides-Extra: dev
